<annotation>
	<folder>train</folder>
	<filename>495.jpg</filename>
	<path>C:\Users\dwiki kusuma\Documents\GitHub\rangrang-ML\workspace\object_detection\images\train\495.jpg</path>
	<source>
		<database>Unknown</database>
	</source>
	<size>
		<width>994</width>
		<height>1500</height>
		<depth>3</depth>
	</size>
	<segmented>0</segmented>
	<object>
		<name>kursi</name>
		<pose>Unspecified</pose>
		<truncated>0</truncated>
		<difficult>0</difficult>
		<bndbox>
			<xmin>100</xmin>
			<ymin>303</ymin>
			<xmax>851</xmax>
			<ymax>1291</ymax>
		</bndbox>
	</object>
</annotation>
