<annotation>
	<folder>pillow</folder>
	<filename>682.jpg</filename>
	<path>D:\wiks\rangrang\new\rangrang-ML-1\downloads\pillow\682.jpg</path>
	<source>
		<database>Unknown</database>
	</source>
	<size>
		<width>1920</width>
		<height>1540</height>
		<depth>1</depth>
	</size>
	<segmented>0</segmented>
	<object>
		<name>bantal</name>
		<pose>Unspecified</pose>
		<truncated>1</truncated>
		<difficult>0</difficult>
		<bndbox>
			<xmin>33</xmin>
			<ymin>1</ymin>
			<xmax>1860</xmax>
			<ymax>1540</ymax>
		</bndbox>
	</object>
</annotation>
