<annotation>
	<folder>train</folder>
	<filename>729.jpg</filename>
	<path>C:\Users\Wahyu Setianto\Desktop\rangrang-ML\workspace\object_detection\images\train\729.jpg</path>
	<source>
		<database>Unknown</database>
	</source>
	<size>
		<width>1500</width>
		<height>1214</height>
		<depth>3</depth>
	</size>
	<segmented>0</segmented>
	<object>
		<name>tanaman</name>
		<pose>Unspecified</pose>
		<truncated>0</truncated>
		<difficult>0</difficult>
		<bndbox>
			<xmin>556</xmin>
			<ymin>42</ymin>
			<xmax>1256</xmax>
			<ymax>1085</ymax>
		</bndbox>
	</object>
	<object>
		<name>buku</name>
		<pose>Unspecified</pose>
		<truncated>0</truncated>
		<difficult>0</difficult>
		<bndbox>
			<xmin>102</xmin>
			<ymin>715</ymin>
			<xmax>753</xmax>
			<ymax>1108</ymax>
		</bndbox>
	</object>
</annotation>
