<annotation>
	<folder>table</folder>
	<filename>788.jpg</filename>
	<path>D:\wiks\rangrang\new\rangrang-ML-1\downloads\table\788.jpg</path>
	<source>
		<database>Unknown</database>
	</source>
	<size>
		<width>2890</width>
		<height>1500</height>
		<depth>3</depth>
	</size>
	<segmented>0</segmented>
	<object>
		<name>meja</name>
		<pose>Unspecified</pose>
		<truncated>0</truncated>
		<difficult>0</difficult>
		<bndbox>
			<xmin>138</xmin>
			<ymin>102</ymin>
			<xmax>2651</xmax>
			<ymax>1472</ymax>
		</bndbox>
	</object>
</annotation>
